nie/__init__.py
nie/aliases.py
nie/client.py
nie/loggers.py
nie/ss/__init__.py
nie/ss/cos/__init__.py
nie/ss/minio/__init__.py
nie/ss/minio/core.py
nie/ss/minio/file.py
nie/ss/minio/op.py
nie/ss/minio/stream.py
nie/ss/minio/text.py
nie/ss/obs/__init__.py
pynie-0.0.2.dist-info/LICENSE
pynie-0.0.2.dist-info/METADATA
pynie-0.0.2.dist-info/WHEEL
pynie-0.0.2.dist-info/top_level.txt
pynie-0.0.2.dist-info/RECORD
