Metadata-Version: 2.1
Name: pynie
Version: 0.0.2
Summary: Generic library for storage level operations
Home-page: https://github.com/ponponon/nie
Author: ponponon
Author-email: 1729303158@qq.com
Maintainer: ponponon
Maintainer-email: 1729303158@qq.com
License: MIT License
Platform: all
Classifier: Programming Language :: Python
Classifier: Programming Language :: Python :: 3.10
Classifier: Topic :: Software Development :: Libraries
License-File: LICENSE
